{
  "3-4": {
    "Cub": [
      "Cover 1 Hole"
,      "Cover 3 Sky"
,      "Gap Press"
,      "OLB Blitz"
,      "Sting Pinch"
,      "Trio Sky Zone"
    ]
,    "Odd": [
      "Cover 1 Hole"
,      "Cover 1 Robber"
,      "Cover 2 Hard Flat"
,      "Cover 3 Match"
,      "Cover 3 Sky"
,      "Cover 4 Drop Show 2"
,      "Cover 4 Quarters"
,      "Cover 6"
,      "Cross 3 Fire"
,      "Pinch Buck 0"
,      "Saw Blitz 1"
,      "SS 2 Trap"
,      "Storm Brave 1"
,      "Tampa 2"
,      "Will Buck 3 Press"
    ]
  },  "4-3": {
    "Odd": [
      "Cover 1 Robber Press"
,      "Cover 2 Man"
,      "Cover 3 Cloud"
,      "Cover 3 Sky"
,      "Cover 6"
,      "LB Dogs"
,      "Pinch 4 Palms"
,      "Strong Slant 3"
,      "Tampa 2"
    ]
,    "Over": [
      "Cover 1 Hole"
,      "Cover 1 Robber Press"
,      "Cover 1 Sting Wk"
,      "Cover 2 Hard Flat"
,      "Cover 2 Man"
,      "Cover 3 Cloud Press"
,      "Cover 3 Sky"
,      "Cover 4 Quarters"
,      "Cover 6"
,      "Free Fire"
,      "OLB Fire Man"
,      "Press Quarters"
,      "Sam Edge 3"
,      "Tampa 2"
,      "Thunder Smoke"
    ]
,    "Under": [
      "2 Invert Hard Flat"
,      "Cover 1 FS Fire"
,      "Cover 1 Hole"
,      "Cover 1 Robber Press"
,      "Cover 1 Slant Crash"
,      "Cover 2 Invert"
,      "Cover 3 Hard Flat"
,      "Cover 3 Match"
,      "Cover 3 Sky Wk"
,      "Cover 4 Quarters"
,      "Free Fire"
,      "FS Fire 3"
,      "Hammer 0 Blast"
,      "Mike Sam Crash Press"
,      "Will Go Fire 3"
    ]
  },  "5-2": {
    "Normal": [
      "Cover 1"
,      "Cover 3"
,      "DT Loop"
,      "Fire Zone 2"
,      "Pinch"
,      "Trio Sky Zone"
    ]
  },  "Dime": {
    "3-2": [
      "1 Double WR1"
,      "1 Double WR2"
,      "Cover 1 Robber Press"
,      "Cover 2 Man"
,      "Cover 3 Buzz Match"
,      "Cover 3 Cloud"
,      "Cover 3 Hard Flat"
,      "Cover 3 Lock"
,      "Cover 4 Drop"
,      "Cover 4 Palms"
,      "Cover 4 Quarters"
,      "Cover 6"
,      "Cover 6 Willie"
,      "DB Fire 2"
,      "Dbl Safety Go"
,      "Double Bracket"
,      "Edge Blitz 1"
,      "Edge Blitz 3"
,      "FS Zone Blitz"
,      "Hot Blitz 3"
,      "Okie Eagle 3"
,      "Okie Roll 2"
,      "Overload 3 Seam Press"
,      "SS Zone Blitz"
,      "Tampa 2"
,      "Tampa 2 Drop"
,      "Zero Blitz"
    ]
,    "Normal": [
      "3 Double Buzz"
,      "Cover 1 Contain"
,      "Cover 1 Robber Press"
,      "Cover 2 Hard Flat"
,      "Cover 2 Man"
,      "Cover 3 Buzz Match"
,      "Cover 3 Buzz Press"
,      "Cover 3 Cloud"
,      "Cover 4 Palms"
,      "Cover 4 Quarters"
,      "Cover 6"
,      "DB Blitz 0"
,      "Dbl Safety Blitz"
,      "Dime Blitz 3"
,      "LB Blitz 1"
,      "Overload 3 Show 2"
,      "SS Blitz 3"
,      "Tampa 2"
    ]
  },  "Goal Line Defense": {
    "5-3": [
      "Gaps A B"
,      "Gaps All"
,      "Gaps All LB"
,      "Gaps B"
,      "GL Man"
,      "MLB Gap A"
    ]
,    "6-2": [
      "60 Half Out"
,      "60 Out"
,      "60 Out Jacks"
,      "60 Pinch"
,      "Base"
,      "Guts"
    ]
  },  "Kick Return": {
    "Landing Zone NFL Kick Return": [
      "Return Left"
,      "Return Middle"
,      "Return Right"
,      "Return Trap Middle"
    ]
,    "Landing Zone NFL Trick Kick Return": [
      "Return Reverse Left "
,      "Return Reverse Right"
,      "Returner Read Option"
    ]
,    "New NFL Kick Return Heavy": [
      "Return Left"
,      "Return Middle"
,      "Return Right"
,      "Return Trap Middle"
    ]
,    "NFL Kick Return": [
      "Return Left Lead"
,      "Return Middle Match Up"
,      "Return Right Lead"
    ]
,    "Onside Base": [
      "Base Onside"
    ]
,    "Onside Heavy": [
      "Onside XL"
    ]
,    "Onside Small": [
      "Hands Team"
    ]
  },  "Nickel": {
    "3-3": [
      "3 Double Buzz"
,      "Cov 2 Invert Hard Flat"
,      "Cover 1 Robber Press"
,      "Cover 2 Drop"
,      "Cover 2 Invert"
,      "Cover 2 Man"
,      "Cover 3 Drop"
,      "Cover 4 Drop"
,      "LB All Go"
,      "LB Blitz 1"
,      "Nickel 2 Trap"
,      "Nickel LB Blitz"
,      "Overload Blitz 3"
,      "SS Mike Blitz"
,      "Tampa 2"
    ]
,    "3-3 Cub": [
      "1 Sam SS Blitz"
,      "3 Sam SS Blitz"
,      "3 Sam Will Blitz"
,      "CB Blitz 2"
,      "Cover 3 Buzz"
,      "Cover 4 Show 2"
,      "LB Blitz 1"
,      "Mike Blitz 0"
,      "Nickel Blitz 3"
,      "OLB Blitz 1"
,      "SS Blitz 0"
,      "Tampa 2"
    ]
,    "Over": [
      "1 Double Slot"
,      "1 Double TE"
,      "1 Double WR1"
,      "1 Double WR2"
,      "Bracket Switch Willie"
,      "Cov 3 Buzz Match WK"
,      "Cover 1 Hole"
,      "Cover 1 LB Blitz"
,      "Cover 1 Robber Press"
,      "Cover 2 Invert"
,      "Cover 2 Man"
,      "Cover 3 Buzz Mable"
,      "Cover 3 Cloud"
,      "Cover 3 Match"
,      "Cover 3 Sky"
,      "Cover 4 Drop Field"
,      "Cover 4 Palms"
,      "Cover 4 Quarters"
,      "Cover 6"
,      "Cover 6 Willie"
,      "Cover 9 Show 2"
,      "Dbl Safety Blitz"
,      "Double Bracket"
,      "Double Bracket Switch"
,      "Edge Blitz 0"
,      "Edge Blitz 3"
,      "Field Sim 3"
,      "FS Will Blitz 0"
,      "Nickel 2 Trap"
,      "Nickel Blitz 3"
,      "Nickel Sim 2"
,      "Over Storm Brave"
,      "Overload 3 Seam"
,      "Overload Blitz"
,      "Sim Pressure 3"
,      "Tampa 2"
    ]
  },  "Prevent": {
    "3 Deep": [
      "3 Deep Blitz"
,      "Cover 1 Contain"
,      "Cover 2 Drop"
,      "Cover 3"
,      "Man 3 Deep"
,      "Prevent"
    ]
  },  "Quarter": {
    "Normal": [
      "3 Double Buzz"
,      "Cover 1 Thief"
,      "Cover 2 Man Spy"
,      "Cover 2 Spy"
,      "Cover 3 Spy"
,      "Cover 4 Drop"
,      "DB Strike 1"
,      "FZ 2 Deep"
,      "FZ 3 Sky"
,      "Man Up 3 Deep"
,      "Overload 3"
,      "Under Smoke"
    ]
  },  "Safety Kick Return": {
    "Landing Zone Heavy Safety Return": [
      "Return Left"
,      "Return Middle"
,      "Return Right"
,      "Return Trap Middle"
    ]
,    "Landing Zone Safety Return": [
      "Return Left"
,      "Return Middle"
,      "Return Right"
,      "Return Trap Middle"
    ]
  },  "Special": {
    "Field Goal Block Left": [
      "Base Block Left"
,      "Load Block Left"
,      "Safe Man Left"
    ]
,    "Field Goal Block Right": [
      "Base Block Right"
,      "Load Block Right"
,      "Safe Man Right"
    ]
,    "Field Goal Return": [
      "FG Block Return"
    ]
,    "Punt Block 44 Even": [
      "8 Up Safe Man"
,      "Squeeze Block"
,      "Straight Rush"
    ]
,    "Punt Return 33 Even": [
      "Return Left"
,      "Return Middle"
,      "Return Right"
    ]
,    "Punt Safe": [
      "Punt Safe Man"
    ]
  }}
